{
  "Version": "2012-10-17",
  "Statement": [
    {
      "Effect": "Allow",
      "Principal": {
        "Federated": "arn:aws:iam::830916170067:oidc-provider/token.actions.githubusercontent.com"
      },
      "Action": "sts:AssumeRoleWithWebIdentity",
      "Condition": {
        "StringEquals": {
          "token.actions.githubusercontent.com:sub": "system:serviceaccount:ops:milestone-organizer-sa",
          "token.actions.githubusercontent.com:aud": "sts.amazonaws.com"
        }
      }
    }
  ]
}
